toncatsu/__init__.py
toncatsu/data_handler.py
toncatsu/matcher_core.py
toncatsu/toncatsu.py
toncatsu-1.0.0.dist-info/licenses/LICENSE
toncatsu-1.0.0.dist-info/METADATA
toncatsu-1.0.0.dist-info/WHEEL
toncatsu-1.0.0.dist-info/top_level.txt
toncatsu-1.0.0.dist-info/RECORD
