Metadata-Version: 2.4
Name: toncatsu
Version: 1.0.0
Summary: A Python Library for Robust Observation-based Map-matching
Author-email: Hiroyuki Hasada <important83d@gmail.com>
License: MIT
Project-URL: Homepage, https://github.com/hasada83d/toncatsu
Project-URL: Repository, https://github.com/hasada83d/toncatsu
Project-URL: Issue Tracker, https://github.com/hasada83d/toncatsu/issues
License-File: LICENSE
Requires-Dist: pandas
Requires-Dist: numpy
Requires-Dist: geopandas
Requires-Dist: shapely
Requires-Dist: networkx
Requires-Dist: scipy
Dynamic: license-file
